llm_discord_bot/bot.py
llm_discord_bot/chatroom.py
llm_discord_bot-2.0.2.dist-info/LICENSE
llm_discord_bot-2.0.2.dist-info/METADATA
llm_discord_bot-2.0.2.dist-info/WHEEL
llm_discord_bot-2.0.2.dist-info/top_level.txt
llm_discord_bot-2.0.2.dist-info/RECORD
