Metadata-Version: 2.1
Name: llm-discord-bot
Version: 2.0.2
Summary: LLM Discord Bot
Home-page: 
Author: Jimming Cheng
Author-email: jimming@gmail.com
Classifier: Programming Language :: Python :: 3
Classifier: License :: OSI Approved :: MIT License
Classifier: Operating System :: OS Independent
License-File: LICENSE
Requires-Dist: arrow
Requires-Dist: discord
Requires-Dist: langchain
Requires-Dist: llm-task-handler
Requires-Dist: pyyaml
